[
  {
    "id": "20260228-IRN-TEH-01",
    "date_utc": "2026-02-28",
    "time_utc": "02:10:00",
    "location_name": "Tehran",
    "latitude": 35.6892,
    "longitude": 51.3890,
    "actor_attacker": "Israel;United States",
    "actor_target": "Iran",
    "event_type": "Airstrike",
    "target_description": "Multiple sites in capital",
    "reported_casualties_min": 30,
    "reported_casualties_max": 60,
    "casualty_confidence": "unconfirmed",
    "sources": "Al Jazeera;ISW;Wikipedia",
    "notes": "Explosions reported across Tehran; casualty figures vary by outlet",
    "geocode_method": "approx_centroid",
    "last_verified": "2026-03-01"
  },
  {
    "id": "20260228-IRN-MINAB-01",
    "date_utc": "2026-02-28",
    "time_utc": "03:05:00",
    "location_name": "Minab",
    "latitude": 27.1461,
    "longitude": 57.0761,
    "actor_attacker": "Israel",
    "actor_target": "Iran",
    "event_type": "Airstrike",
    "target_description": "Alleged hit near girls' elementary school",
    "reported_casualties_min": 108,
    "reported_casualties_max": 108,
    "casualty_confidence": "disputed",
    "sources": "Al Jazeera;Wikipedia",
    "notes": "State media reports large civilian toll at school; figures contested",
    "geocode_method": "manual",
    "last_verified": "2026-03-01"
  },
  {
    "id": "20260228-IRN-KONARAK-01",
    "date_utc": "2026-02-28",
    "time_utc": "04:00:00",
    "location_name": "Konarak Naval Area",
    "latitude": 25.4000,
    "longitude": 59.0000,
    "actor_attacker": "Israel",
    "actor_target": "Iran",
    "event_type": "Naval/Airstrike",
    "target_description": "Naval base and vessels damaged",
    "reported_casualties_min": null,
    "reported_casualties_max": null,
    "casualty_confidence": "unconfirmed",
    "sources": "ISW;Wikipedia",
    "notes": "Satellite imagery and local reports indicate damage to vessels",
    "geocode_method": "approx_centroid",
    "last_verified": "2026-03-01"
  },
  {
    "id": "20260228-IRN-NATFAC-01",
    "date_utc": "2026-02-28",
    "time_utc": "02:45:00",
    "location_name": "Undisclosed Nuclear Site",
    "latitude": 33.0000,
    "longitude": 52.0000,
    "actor_attacker": "Israel;United States",
    "actor_target": "Iran",
    "event_type": "Airstrike",
    "target_description": "Military/nuclear infrastructure",
    "reported_casualties_min": 15,
    "reported_casualties_max": 40,
    "casualty_confidence": "unconfirmed",
    "sources": "ISW;Wikipedia",
    "notes": "Target described as military/nuclear infrastructure; exact site withheld",
    "geocode_method": "geocoded_from_text",
    "last_verified": "2026-03-01"
  },
  {
    "id": "20260228-IRN-HORMOZ-01",
    "date_utc": "2026-02-28",
    "time_utc": "05:20:00",
    "location_name": "Strait of Hormuz",
    "latitude": 26.5667,
    "longitude": 56.2500,
    "actor_attacker": "Iran",
    "actor_target": "International shipping",
    "event_type": "Missile/Sea strike",
    "target_description": "Area closure and attacks on shipping",
    "reported_casualties_min": 0,
    "reported_casualties_max": 10,
    "casualty_confidence": "unconfirmed",
    "sources": "Al Jazeera;ISW",
    "notes": "IRGC announced closure; reports of missile launches into shipping lanes",
    "geocode_method": "approx_centroid",
    "last_verified": "2026-03-01"
  },
  {
    "id": "20260228-IRN-TEH-02",
    "date_utc": "2026-02-28",
    "time_utc": "02:30:00",
    "location_name": "Tehran Suburb",
    "latitude": 35.7000,
    "longitude": 51.4000,
    "actor_attacker": "Israel",
    "actor_target": "Iran",
    "event_type": "Airstrike",
    "target_description": "Government compound/leadership target",
    "reported_casualties_min": 5,
    "reported_casualties_max": 25,
    "casualty_confidence": "unconfirmed",
    "sources": "ISW;Wikipedia",
    "notes": "Reports of decapitation strikes on senior officials; details limited",
    "geocode_method": "approx_centroid",
    "last_verified": "2026-03-01"
  },
  {
    "id": "20260228-IRN-SHIRAZ-01",
    "date_utc": "2026-02-28",
    "time_utc": "03:40:00",
    "location_name": "Shiraz",
    "latitude": 29.5918,
    "longitude": 52.5836,
    "actor_attacker": "Israel",
    "actor_target": "Iran",
    "event_type": "Airstrike",
    "target_description": "Military logistics hub",
    "reported_casualties_min": 2,
    "reported_casualties_max": 12,
    "casualty_confidence": "unconfirmed",
    "sources": "ISW;Al Jazeera",
    "notes": "Local outlets report strikes on logistics and storage facilities",
    "geocode_method": "geocoded_from_text",
    "last_verified": "2026-03-01"
  },
  {
    "id": "20260228-IRN-ABADAN-01",
    "date_utc": "2026-02-28",
    "time_utc": "04:10:00",
    "location_name": "Abadan",
    "latitude": 30.3470,
    "longitude": 48.2933,
    "actor_attacker": "Israel",
    "actor_target": "Iran",
    "event_type": "Missile Strike",
    "target_description": "Oil infrastructure and storage",
    "reported_casualties_min": 0,
    "reported_casualties_max": 5,
    "casualty_confidence": "unconfirmed",
    "sources": "Al Jazeera;ISW",
    "notes": "Reports of strikes near oil terminals; commercial impact noted",
    "geocode_method": "approx_centroid",
    "last_verified": "2026-03-01"
  },
  {
    "id": "20260228-IRN-IRGCBASE-01",
    "date_utc": "2026-02-28",
    "time_utc": "03:55:00",
    "location_name": "Isfahan Military Complex",
    "latitude": 32.6546,
    "longitude": 51.6680,
    "actor_attacker": "Israel;United States",
    "actor_target": "Iran",
    "event_type": "Airstrike",
    "target_description": "IRGC command and control node",
    "reported_casualties_min": 10,
    "reported_casualties_max": 30,
    "casualty_confidence": "unconfirmed",
    "sources": "ISW;Wikipedia",
    "notes": "Analysts report strikes on command nodes; casualty estimates vary",
    "geocode_method": "geocoded_from_text",
    "last_verified": "2026-03-01"
  },
  {
    "id": "20260228-REG-ISR-01",
    "date_utc": "2026-02-28",
    "time_utc": "06:10:00",
    "location_name": "Southern Israel",
    "latitude": 31.0461,
    "longitude": 34.8516,
    "actor_attacker": "Iran",
    "actor_target": "Israel",
    "event_type": "Missile Strike",
    "target_description": "Missile impacts and air defenses engaged",
    "reported_casualties_min": 0,
    "reported_casualties_max": 8,
    "casualty_confidence": "unconfirmed",
    "sources": "Al Jazeera;ISW",
    "notes": "Iranian missile salvos reported toward Israel; air defenses activated",
    "geocode_method": "approx_centroid",
    "last_verified": "2026-03-01"
  },
  {
    "id": "20260228-REG-USBASE-01",
    "date_utc": "2026-02-28",
    "time_utc": "06:40:00",
    "location_name": "Al Udeid Air Base",
    "latitude": 25.1853,
    "longitude": 51.3167,
    "actor_attacker": "Iran",
    "actor_target": "United States",
    "event_type": "Missile Strike",
    "target_description": "US base targeted in region",
    "reported_casualties_min": 0,
    "reported_casualties_max": 6,
    "casualty_confidence": "unconfirmed",
    "sources": "ISW;Al Jazeera",
    "notes": "Iranian missiles reported toward US regional bases; damage reports mixed",
    "geocode_method": "manual",
    "last_verified": "2026-03-01"
  },
  {
    "id": "20260229-IRN-RETAL-01",
    "date_utc": "2026-02-29",
    "time_utc": "07:00:00",
    "location_name": "Multiple Gulf Locations",
    "latitude": 25.0000,
    "longitude": 54.0000,
    "actor_attacker": "Iran",
    "actor_target": "Regional States",
    "event_type": "Missile/Drone Strikes",
    "target_description": "Strikes across Bahrain Saudi Qatar UAE Iraq",
    "reported_casualties_min": 5,
    "reported_casualties_max": 50,
    "casualty_confidence": "disputed",
    "sources": "Al Jazeera;ISW;Wikipedia",
    "notes": "Iran launched regional strikes in retaliation; casualty reports vary by country",
    "geocode_method": "approx_centroid",
    "last_verified": "2026-03-01"
  }
]
